dispander/__init__.py
dispander/module.py
dispander-0.5.0.dist-info/LICENSE
dispander-0.5.0.dist-info/METADATA
dispander-0.5.0.dist-info/WHEEL
dispander-0.5.0.dist-info/top_level.txt
dispander-0.5.0.dist-info/RECORD
