Metadata-Version: 2.1
Name: dispander
Version: 0.5.0
Summary: Discord Message URL Expander
Home-page: https://github.com/DiscordBotPortalJP/dispander
Author: 1ntegrale9
Author-email: 1ntegrale9uation@gmail.com
License: UNKNOWN
Platform: UNKNOWN
Classifier: Programming Language :: Python :: 3.7
Classifier: License :: OSI Approved :: MIT License
Classifier: Operating System :: OS Independent
License-File: LICENSE
Requires-Dist: discord.py (>=1.3.3)
